LICENSE
README.md
setup.py
instagrapi/__init__.py
instagrapi/config.py
instagrapi/exceptions.py
instagrapi/extractors.py
instagrapi/image_util.py
instagrapi/story.py
instagrapi/types.py
instagrapi/utils.py
instagrapi/zones.py
instagrapi/mixins/__init__.py
instagrapi/mixins/account.py
instagrapi/mixins/album.py
instagrapi/mixins/auth.py
instagrapi/mixins/bloks.py
instagrapi/mixins/challenge.py
instagrapi/mixins/clip.py
instagrapi/mixins/collection.py
instagrapi/mixins/comment.py
instagrapi/mixins/direct.py
instagrapi/mixins/explore.py
instagrapi/mixins/fbsearch.py
instagrapi/mixins/fundraiser.py
instagrapi/mixins/hashtag.py
instagrapi/mixins/highlight.py
instagrapi/mixins/igtv.py
instagrapi/mixins/insights.py
instagrapi/mixins/location.py
instagrapi/mixins/media.py
instagrapi/mixins/multiple_accounts.py
instagrapi/mixins/note.py
instagrapi/mixins/notification.py
instagrapi/mixins/password.py
instagrapi/mixins/photo.py
instagrapi/mixins/private.py
instagrapi/mixins/public.py
instagrapi/mixins/share.py
instagrapi/mixins/signup.py
instagrapi/mixins/story.py
instagrapi/mixins/timeline.py
instagrapi/mixins/totp.py
instagrapi/mixins/track.py
instagrapi/mixins/user.py
instagrapi/mixins/video.py
yourname_instagrapi.egg-info/PKG-INFO
yourname_instagrapi.egg-info/SOURCES.txt
yourname_instagrapi.egg-info/dependency_links.txt
yourname_instagrapi.egg-info/requires.txt
yourname_instagrapi.egg-info/top_level.txt